ebclient/__init__.py
ebclient/crypto_util.py
ebclient/eb_base_utils.py
ebclient/eb_configuration.py
ebclient/eb_create_uo.py
ebclient/eb_registration.py
ebclient/eb_request.py
ebclient/eb_utils.py
ebclient/errors.py
ebclient/process_data.py
ebclient/py3compat.py
ebclient/uo.py
ebclient/create_uo/__init__.py
ebclient/create_uo/Environment/__init__.py
ebclient/create_uo/Gen/__init__.py
ebclient/create_uo/KeyTypes/__init__.py
ebclient/create_uo/TemplateFields/__init__.py
ebclient/eb_consts/__init__.py
ebclient/eb_consts/EBConsts/__init__.py
ebclient/eb_consts/UOTypes/__init__.py
ebclient/registration/__init__.py
ebclient/tests/__init__.py
ebclient/tests/create_uo_test.py
ebclient/tests/process_data_test.py
ebclient/tests/registration_test.py
ebclient-1.1.17.dist-info/METADATA
ebclient-1.1.17.dist-info/RECORD
ebclient-1.1.17.dist-info/WHEEL
ebclient-1.1.17.dist-info/top_level.txt
