Metadata-Version: 2.1
Name: ebclient
Version: 1.1.17
Summary: EnigmaBridge Python Client
Home-page: https://github.com/EnigmaBridge/client.py
Author: Enigma Bridge
Author-email: support@enigmabridge.com
License: MIT License
Requires-Dist: pycrypto (>=2.6)
Requires-Dist: requests
Requires-Dist: setuptools (>=1.0)
Requires-Dist: six
Requires-Dist: Crypto
Requires-Dist: future
Requires-Dist: mock
Provides-Extra: dev
Requires-Dist: nose; extra == 'dev'
Requires-Dist: pep8; extra == 'dev'
Requires-Dist: tox; extra == 'dev'
Provides-Extra: docs
Requires-Dist: Sphinx (>=1.0); extra == 'docs'
Requires-Dist: sphinx-rtd-theme; extra == 'docs'
Requires-Dist: sphinxcontrib-programoutput; extra == 'docs'
